pymenu/__init__.py
pymenu/auto_menu.py
pymenu/menu.py
pymenu/option.py
pymenu/select_menu.py
pymenu/utils/__init__.py
pymenu/utils/inputs.py
pymenu/utils/keyboard.py
pymenu_console-0.2.1.dist-info/LICENSE
pymenu_console-0.2.1.dist-info/METADATA
pymenu_console-0.2.1.dist-info/WHEEL
pymenu_console-0.2.1.dist-info/top_level.txt
pymenu_console-0.2.1.dist-info/RECORD
