Metadata-Version: 2.1
Name: pymenu-console
Version: 0.2.1
Summary: Python console menu
Home-page: https://github.com/luanws/pymenu
Author: luanws
Author-email: luan.w.silveira@gmail.com
License: UNKNOWN
Platform: UNKNOWN
Classifier: Programming Language :: Python :: 3
Classifier: License :: OSI Approved :: MIT License
Classifier: Operating System :: OS Independent
Requires-Python: >=3.7
Requires-Dist: termcolor
Requires-Dist: readchar
